<ns0:entry xmlns:ns0="http://www.w3.org/2005/Atom" xmlns:ns1="http://arxiv.org/schemas/atom">
    <ns0:id>http://arxiv.org/abs/1412.5335v7</ns0:id>
    <ns0:updated>2015-05-27T06:40:09Z</ns0:updated>
    <ns0:published>2014-12-17T11:02:04Z</ns0:published>
    <ns0:title>Ensemble of Generative and Discriminative Techniques for Sentiment
  Analysis of Movie Reviews</ns0:title>
    <ns0:summary>  Sentiment analysis is a common task in natural language processing that aims
to detect polarity of a text document (typically a consumer review). In the
simplest settings, we discriminate only between positive and negative
sentiment, turning the task into a standard binary classification problem. We
compare several ma- chine learning approaches to this problem, and combine them
to achieve the best possible results. We show how to use for this task the
standard generative lan- guage models, which are slightly complementary to the
state of the art techniques. We achieve strong results on a well-known dataset
of IMDB movie reviews. Our results are easily reproducible, as we publish also
the code needed to repeat the experiments. This should simplify further advance
of the state of the art, as other researchers can combine their techniques with
ours with little effort.
</ns0:summary>
    <ns0:author>
      <ns0:name>Gr&#233;goire Mesnil</ns0:name>
    </ns0:author>
    <ns0:author>
      <ns0:name>Tomas Mikolov</ns0:name>
    </ns0:author>
    <ns0:author>
      <ns0:name>Marc'Aurelio Ranzato</ns0:name>
    </ns0:author>
    <ns0:author>
      <ns0:name>Yoshua Bengio</ns0:name>
    </ns0:author>
    <ns0:link href="http://arxiv.org/abs/1412.5335v7" rel="alternate" type="text/html" />
    <ns0:link title="pdf" href="http://arxiv.org/pdf/1412.5335v7" rel="related" type="application/pdf" />
    <ns1:primary_category term="cs.CL" scheme="http://arxiv.org/schemas/atom" />
    <ns0:category term="cs.CL" scheme="http://arxiv.org/schemas/atom" />
    <ns0:category term="cs.IR" scheme="http://arxiv.org/schemas/atom" />
    <ns0:category term="cs.LG" scheme="http://arxiv.org/schemas/atom" />
    <ns0:category term="cs.NE" scheme="http://arxiv.org/schemas/atom" />
  </ns0:entry>
